logbetter/__init__.py
logbetter/logbetter.py
logbetter-0.0.2.dist-info/METADATA
logbetter-0.0.2.dist-info/WHEEL
logbetter-0.0.2.dist-info/licenses/LICENSE
logbetter-0.0.2.dist-info/RECORD
